{"(1, 1, 1, 1, 1)": "(n**4 - 20*n**2 + 78)/(n*(n - 4)*(n - 3)*(n - 2)*(n - 1)*(n + 1)*(n + 2)*(n + 3)*(n + 4))", "(2, 1, 1, 1)": "-(n**2 - 12)*(n**2 - 2)/(n**2*(n - 4)*(n - 3)*(n - 2)*(n - 1)*(n + 1)*(n + 2)*(n + 3)*(n + 4))", "(3, 1, 1)": "2/(n*(n - 4)*(n - 2)*(n - 1)*(n + 1)*(n + 2)*(n + 4))", "(2, 2, 1)": "(n**2 - 2)/(n*(n - 4)*(n - 3)*(n - 2)*(n - 1)*(n + 1)*(n + 2)*(n + 3)*(n + 4))", "(4, 1)": "(24 - 5*n**2)/(n**2*(n - 4)*(n - 3)*(n - 2)*(n - 1)*(n + 1)*(n + 2)*(n + 3)*(n + 4))", "(3, 2)": "-2*(n**2 + 12)/(n**2*(n - 4)*(n - 3)*(n - 2)*(n - 1)*(n + 1)*(n + 2)*(n + 3)*(n + 4))", "(5,)": "14/(n*(n - 4)*(n - 3)*(n - 2)*(n - 1)*(n + 1)*(n + 2)*(n + 3)*(n + 4))"}